{
  "taxes": {
    "stateDisabilityInsurance": {
      "rate": [
        [0, 0.01],
        [114967, 0]
      ],
      "source": {
        "name": "State of California - Rates, Withholding Schedules, and Meals and Lodging Values",
        "url": "//www.edd.ca.gov/payroll_taxes/rates_and_withholding.htm"
      }
    },
    "mentalHealthServices": {
      "rate": [
        [0, 0],
        [1000000, 0.01]
      ],
      "source": {
        "name": "Mental Health Services Act (MHSA)",
        "url": "//www.dhcs.ca.gov/services/mh/Pages/MH_Prop63.aspx"
      }
    },
    "income": {
      "rate": {
        "single": [
          [0, 0.01],
          [8223, 0.02],
          [19495, 0.03],
          [30769, 0.04],
          [42711, 0.08],
          [53980, 0.093],
          [275738, 0.103],
          [330884, 0.113],
          [551473, 0.123]
        ],
        "married": [
          [0, 0.01],
          [16446, 0.02],
          [38990, 0.04],
          [61538, 0.06],
          [85422, 0.08],
          [107960, 0.093],
          [551476, 0.103],
          [661768, 0.113],
          [1074996, 0.123]
        ]
      },
      "deductions": {
        "standardDeduction": {
          "amount": {
            "single": 4236,
            "married": 8472
          }
        },
        "personalExemption": {
          "amount": {
            "single": 114,
            "married": 228
          },
          "phaseout": {
            "single": {
              "start": 178706,
              "step": 2500,
              "reduction": 6,
              "minimum": 0
            },
            "married": {
              "start": 357417,
              "step": 2500,
              "reduction": 12,
              "minimum": 0
            }
          }
        },
        "dependents": {
          "amount": 353,
          "phaseout": {
            "single": {
              "start": 178706,
              "step": 2500,
              "reduction": 6,
              "minimum": 0
            },
            "married": {
              "start": 357417,
              "step": 2500,
              "reduction": 12,
              "minimum": 0
            }
          }
        }
      },
      "source": {
        "name": "State Individual Income Tax Rates and Brackets for 2018 | Tax Foundation",
        "url": "//taxfoundation.org/state-individual-income-tax-rates-brackets-2018/"
      }
    },
    "amt": {
      "rate": 0.07,
      "deductions": {
        "amtExemption": {
          "amount": {
            "single": 71531,
            "married": 95373
          },
          "phaseout": {
            "single": {
              "start": 268237,
              "step": 400,
              "reduction": 100,
              "minimum": 0
            },
            "married": {
              "start": 357650,
              "step": 400,
              "reduction": 100,
              "minimum": 0
            }
          }
        }
      },
      "source": {
        "name": "2018 Schedule P (540) - Alternative Minimum Tax and Credit Limitations - Residents",
        "url": "//www.ftb.ca.gov/forms/2018/18_540p.pdf"
      }
    }
  }
}